azurepricingapi/__init__.py
azurepricingapi/index.py
azurepricingapi-0.3.0.dist-info/LICENSE
azurepricingapi-0.3.0.dist-info/METADATA
azurepricingapi-0.3.0.dist-info/WHEEL
azurepricingapi-0.3.0.dist-info/top_level.txt
azurepricingapi-0.3.0.dist-info/RECORD
